setup.py
graphstar/__init__.py
graphstar/graph.py
graphstar/heuristic.py
graphstar/search.py
graphstar/utils.py
graphstar.egg-info/PKG-INFO
graphstar.egg-info/SOURCES.txt
graphstar.egg-info/dependency_links.txt
graphstar.egg-info/not-zip-safe
graphstar.egg-info/pbr.json
graphstar.egg-info/top_level.txt