Metadata-Version: 1.0
Name: graphstar
Version: 0.1
Summary: Simple graph with pathfinding
Home-page: https://github.com/pengboomouch/graphstar
Author: pengboomouch (Cristian Cornea)
Author-email: pengboomouch@gmail.com
License: MIT
Platform: UNKNOWN
